{
  "main": {
    "id": "5b00d314e71469f4",
    "type": "split",
    "children": [
      {
        "id": "e7cb730ec9b80b18",
        "type": "tabs",
        "children": [
          {
            "id": "2a008df85dd4325f",
            "type": "leaf",
            "state": {
              "type": "markdown",
              "state": {
                "file": "Tags/Virtualization.md",
                "mode": "source",
                "backlinks": true,
                "source": false
              },
              "icon": "lucide-file",
              "title": "Virtualization"
            }
          },
          {
            "id": "06f9b3e36979c05a",
            "type": "leaf",
            "state": {
              "type": "markdown",
              "state": {
                "file": "Indexes/Drone Project.md",
                "mode": "source",
                "backlinks": true,
                "source": false
              },
              "icon": "lucide-file",
              "title": "Drone Project"
            }
          }
        ]
      }
    ],
    "direction": "vertical"
  },
  "left": {
    "id": "5cfc28777eceabe7",
    "type": "mobile-drawer",
    "children": [
      {
        "id": "11c19a654a8bdc13",
        "type": "leaf",
        "state": {
          "type": "file-explorer",
          "state": {
            "sortOrder": "alphabetical"
          },
          "icon": "lucide-folder-closed",
          "title": "Files"
        }
      },
      {
        "id": "0d762c7f90e5a012",
        "type": "leaf",
        "state": {
          "type": "search",
          "state": {
            "query": "",
            "matchingCase": false,
            "explainSearch": false,
            "collapseAll": false,
            "extraContext": false,
            "sortOrder": "alphabetical"
          },
          "icon": "lucide-search",
          "title": "Search"
        }
      },
      {
        "id": "a01dc89b2436f445",
        "type": "leaf",
        "state": {
          "type": "tag",
          "state": {
            "sortOrder": "frequency",
            "useHierarchy": true
          },
          "icon": "lucide-tags",
          "title": "Tags"
        }
      },
      {
        "id": "88c222427136d0e8",
        "type": "leaf",
        "state": {
          "type": "bookmarks",
          "state": {},
          "icon": "lucide-bookmark",
          "title": "Bookmarks"
        }
      }
    ],
    "currentTab": 0
  },
  "right": {
    "id": "ad522054230588e7",
    "type": "mobile-drawer",
    "children": [
      {
        "id": "e885bb0ba2cfa36b",
        "type": "leaf",
        "state": {
          "type": "backlink",
          "state": {
            "file": "Zettelkasten/Introduzione Probabilità, Analisi Combinatoria.md",
            "collapseAll": false,
            "extraContext": false,
            "sortOrder": "alphabetical",
            "showSearch": false,
            "searchQuery": "",
            "backlinkCollapsed": false,
            "unlinkedCollapsed": true
          },
          "icon": "links-coming-in",
          "title": "Backlinks"
        }
      },
      {
        "id": "5748d4e154321979",
        "type": "leaf",
        "state": {
          "type": "outgoing-link",
          "state": {
            "file": "Source Material/TUTTO MATEMATICA DISCRETA E CODICI.pdf",
            "linksCollapsed": false,
            "unlinkedCollapsed": true
          },
          "icon": "links-going-out",
          "title": "Outgoing links"
        }
      },
      {
        "id": "3a8867b4c2368a81",
        "type": "leaf",
        "state": {
          "type": "outline",
          "state": {
            "file": "Source Material/TUTTO MATEMATICA DISCRETA E CODICI.pdf"
          },
          "icon": "lucide-list",
          "title": "Outline"
        }
      },
      {
        "id": "45a85addc1bb5a91",
        "type": "leaf",
        "state": {
          "type": "git-view",
          "state": {},
          "icon": "git-pull-request",
          "title": "Source Control"
        }
      },
      {
        "id": "1088bf82243a96f6",
        "type": "leaf",
        "state": {
          "type": "mermaid-toolbar-view",
          "state": {},
          "icon": "trident-custom",
          "title": "Mermaid Toolbar"
        }
      }
    ],
    "currentTab": 3
  },
  "left-ribbon": {
    "hiddenItems": {
      "switcher:Open quick switcher": false,
      "graph:Open graph view": false,
      "canvas:Create new canvas": false,
      "daily-notes:Open today's daily note": false,
      "templates:Insert template": false,
      "command-palette:Open command palette": false,
      "obsidian-git:Open Git source control": false,
      "mermaid-tools:Open Mermaid Toolbar": false,
      "obsidian-excalidraw-plugin:Create new drawing": false
    }
  },
  "active": "45a85addc1bb5a91",
  "lastOpenFiles": [
    "/Zettelkasten/Funzioni Reali di Variabile Reale.md",
    "Zettelkasten/QEMU-KVM-libvirt.md",
    "Indexes/Drone Project.md",
    "Tags/Virtualization.md",
    "QEMU/KVM/libvirt.md",
    "QEMU",
    "QEMU/KVM",
    "Indexes/Linux.md",
    "Zettelkasten/Battery.md",
    "Zettelkasten/Propellers.md",
    "Zettelkasten/PID Control.md",
    "Zettelkasten/FPV System.md",
    "Zettelkasten/Flight Controller.md",
    "Zettelkasten/ESC Theory.md",
    "Zettelkasten/ESC.md",
    "Zettelkasten/Motors.md",
    "Zettelkasten/Electromotive and Back Electromotive Force.md",
    "Zettelkasten/Motors Theory.md",
    "Source Material/Images/Pasted image 20250118153551.jpg",
    "Zettelkasten/Batteries Theory.md",
    "Source Material/Images/Pasted image 20250118124916.png",
    "Source Material/Images/Pasted image 20250118105341.png",
    "Source Material/Images/Pasted image 20250118105102.png",
    "Source Material/Images/Pasted image 20250118105000.jpg",
    "Zettelkasten/Frame.md",
    "Zettelkasten/Remote Control.md",
    "Excalidraw/Esercizi Analisi 2.md",
    "Zettelkasten/Ottimizzazione.md",
    "Tags/Analisi 2 e Probabilità.md",
    "Zettelkasten/Calcolo Differenziale.md",
    "Zettelkasten/Continuità, Max & Min.md",
    "Source Material/Images/SoluzioniFoglio2 2_07442914581f35737af5af4146529aff.pdf",
    "Source Material/Images/Esercizi_Foglio2_bd265c7c9c695a504c22f417c678d2a2.pdf",
    "Indexes/University.md",
    "Zettelkasten/Limiti e Continuità per Funzioni di più Variabili.md",
    "Source Material/Images/Pasted image 20250115124737.jpg",
    "Source Material/Images/Pasted image 20250115124541.jpg",
    "Source Material/Images/Pasted image 20250115124508.jpg",
    "Untitled 2.canvas",
    "Untitled 1.canvas",
    "Source Material/Images/Ink/Writing/2025.1.13 - 11.56am.writing",
    "Source Material/Images/Ink/Writing",
    "Source Material/Images/Ink",
    "Source Material/Images/Soluzioni Foglio 1_4f5488090d829062ed4d1eac1d944a68.pdf",
    "Source Material/Images/Esercizi_Foglio1_f6901d5714f6ff8f3620099dcf69d450.pdf",
    "Source Material/Images/Immagine 21.jpeg",
    "Source Material/Images/Pasted image 20250111174731.png",
    "Untitled.canvas",
    "Source Material/PDFs/Lebesgue.pdf"
  ]
}